terminal_help_app/__init__.py
terminal_help_app/chatgpt.py
terminal_help_app/main.py
terminal_help_app/settings.py
terminal_help_app/structured_printer.py
terminal_help_app/helper/__init__.py
terminal_help_app/helper/db.py
terminal_help_app/helper/partial_json_parse.py
terminal_help_app/helper/serde.py
terminal_help_app/helper/system_helper.py
terminal_help_app-0.1.0.dist-info/METADATA
terminal_help_app-0.1.0.dist-info/WHEEL
terminal_help_app-0.1.0.dist-info/entry_points.txt
terminal_help_app-0.1.0.dist-info/RECORD
