Metadata-Version: 2.4
Name: terminal-help-app
Version: 0.1.0
Summary: command-line tool `help` to write terminal commands for you using natural language powered by ChatGPT
Project-URL: Homepage, https://github.com/Submersible/terminal-help-app
Project-URL: Documentation, https://github.com/Submersible/terminal-help-app
Project-URL: Issue Tracker, https://github.com/Submersiblet/terminal-help-app/issues
Author-email: Ryan Munro <500774+munro@users.noreply.github.com>
License: MIT
Classifier: Environment :: Console
Classifier: Environment :: MacOS X
Classifier: Intended Audience :: Developers
Classifier: Intended Audience :: End Users/Desktop
Classifier: Intended Audience :: System Administrators
Classifier: License :: OSI Approved :: MIT License
Classifier: Natural Language :: English
Classifier: Programming Language :: Python :: 3.12
Classifier: Topic :: Utilities
Requires-Python: <3.13,>=3.12
Requires-Dist: colorama>=0.4.6
Requires-Dist: httpx<0.29,>=0.27.0
Requires-Dist: loguru>=0.7.3
Requires-Dist: openai<1.66,>1.40.6
Requires-Dist: partialjson<0.2,>=0.0.8
Requires-Dist: prompt-toolkit<3.1,>=3.0.39
Requires-Dist: pydantic<2.20,>=2.8.2
Requires-Dist: pygments<2.20,>2.16.1
